{
  "sample_note": "Abridged example based on WidgetMenu_Original.uasset. The full uasset_to_text.py output includes more fields and table entries.",
  "file": {
    "path": "local_test_assets/UE427_UMG/WidgetMenu_Original.uasset",
    "size": 46391
  },
  "summary": {
    "effective_file_version_ue4": 522,
    "name_count": 203,
    "import_count": 41,
    "export_count": 42,
    "package_source": 2887956606
  },
  "names": [
    {
      "index": 195,
      "value": "Widget Menu"
    },
    {
      "index": 198,
      "value": "WidgetMenu"
    },
    {
      "index": 199,
      "value": "WidgetMenu_C"
    },
    {
      "index": 201,
      "value": "WidgetTree"
    }
  ],
  "imports": [
    {
      "index": 14,
      "path": "/Script/UMG.Button",
      "class": "/Script/CoreUObject.Class"
    },
    {
      "index": 16,
      "path": "/Script/UMG.TextBlock",
      "class": "/Script/CoreUObject.Class"
    },
    {
      "index": 17,
      "path": "/Script/UMG.UserWidget",
      "class": "/Script/CoreUObject.Class"
    },
    {
      "index": 20,
      "path": "/Script/UMG.WidgetBlueprintGeneratedClass",
      "class": "/Script/CoreUObject.Class"
    },
    {
      "index": 22,
      "path": "/Script/UMGEditor.WidgetBlueprint",
      "class": "/Script/CoreUObject.Class"
    }
  ],
  "exports": [
    {
      "index": 37,
      "object_name": {
        "index": 198,
        "number": 0,
        "value": "WidgetMenu"
      },
      "path": "WidgetMenu",
      "class": "/Script/UMGEditor.WidgetBlueprint",
      "super": null,
      "is_asset": true
    },
    {
      "index": 38,
      "object_name": {
        "index": 199,
        "number": 0,
        "value": "WidgetMenu_C"
      },
      "path": "WidgetMenu_C",
      "class": "/Script/UMG.WidgetBlueprintGeneratedClass",
      "super": "/Script/UMG.UserWidget",
      "is_asset": true
    },
    {
      "index": 40,
      "object_name": {
        "index": 201,
        "number": 0,
        "value": "WidgetTree"
      },
      "path": "WidgetMenu.WidgetTree",
      "class": "/Script/UMG.WidgetTree",
      "super": null,
      "is_asset": false
    },
    {
      "index": 0,
      "object_name": {
        "index": 31,
        "number": 1,
        "value": "Border_0"
      },
      "path": "WidgetMenu.WidgetTree.Border_0",
      "class": "/Script/UMG.Border",
      "super": null,
      "is_asset": false
    },
    {
      "index": 4,
      "object_name": {
        "index": 92,
        "number": 0,
        "value": "ExitButton"
      },
      "path": "WidgetMenu.WidgetTree.ExitButton",
      "class": "/Script/UMG.Button",
      "super": null,
      "is_asset": false
    },
    {
      "index": 5,
      "object_name": {
        "index": 154,
        "number": 0,
        "value": "RestartButton"
      },
      "path": "WidgetMenu.WidgetTree.RestartButton",
      "class": "/Script/UMG.Button",
      "super": null,
      "is_asset": false
    },
    {
      "index": 27,
      "object_name": {
        "index": 177,
        "number": 0,
        "value": "Text_ExitButton"
      },
      "path": "WidgetMenu.WidgetTree.Text_ExitButton",
      "class": "/Script/UMG.TextBlock",
      "super": null,
      "is_asset": false
    },
    {
      "index": 28,
      "object_name": {
        "index": 178,
        "number": 0,
        "value": "Text_RestartButton"
      },
      "path": "WidgetMenu.WidgetTree.Text_RestartButton",
      "class": "/Script/UMG.TextBlock",
      "super": null,
      "is_asset": false
    },
    {
      "index": 31,
      "object_name": {
        "index": 192,
        "number": 49,
        "value": "VerticalBox_48"
      },
      "path": "WidgetMenu.WidgetTree.VerticalBox_48",
      "class": "/Script/UMG.VerticalBox",
      "super": null,
      "is_asset": false
    }
  ],
  "depends": [],
  "soft_package_references": [],
  "preload_dependencies": []
}
